jsonshift/__init__.py
jsonshift/cli.py
jsonshift/exceptions.py
jsonshift/mapper.py
jsonshift-1.2.0.dist-info/licenses/LICENSE
jsonshift-1.2.0.dist-info/METADATA
jsonshift-1.2.0.dist-info/WHEEL
jsonshift-1.2.0.dist-info/entry_points.txt
jsonshift-1.2.0.dist-info/top_level.txt
jsonshift-1.2.0.dist-info/RECORD
