Metadata-Version: 2.4
Name: jsonshift
Version: 1.2.0
Summary: A deterministic JSON payload mapper that transforms source data into target structures using dotted paths, indices and wildcards.
Author-email: pml-guardian <pml@guardian-asset.com>
License: MIT
Project-URL: Homepage, https://github.com/pml-guardian/jsonshift
Project-URL: Documentation, https://github.com/pml-guardian/jsonshift#readme
Project-URL: Issues, https://github.com/pml-guardian/jsonshift/issues
Keywords: json,mapping,transform,payload,data,mapper,integration,etl,adapter
Classifier: Programming Language :: Python :: 3
Classifier: Programming Language :: Python :: 3 :: Only
Classifier: License :: OSI Approved :: MIT License
Classifier: Operating System :: OS Independent
Classifier: Topic :: Software Development :: Libraries
Classifier: Topic :: Software Development :: Libraries :: Python Modules
Requires-Python: >=3.9
License-File: LICENSE
Provides-Extra: dev
Requires-Dist: pytest>=8.4.2; extra == "dev"
Dynamic: license-file
